tails_of_words/__analyzer__.py
tails_of_words/__config__.py
tails_of_words/__distance__.py
tails_of_words/__init__.py
tails_of_words/__main__.py
tails_of_words/__swing__.py
tails_of_words/__typo__.py
tails_of_words/__words__.py
tails_of_words-2.0.0.dist-info/LICENSE
tails_of_words-2.0.0.dist-info/METADATA
tails_of_words-2.0.0.dist-info/WHEEL
tails_of_words-2.0.0.dist-info/entry_points.txt
tails_of_words-2.0.0.dist-info/top_level.txt
tails_of_words-2.0.0.dist-info/RECORD
