Metadata-Version: 2.1
Name: tails-of-words
Version: 2.0.0
Summary: .
Home-page: https://github.com/srz-zumix/tails-of-words/
Author: srz_zumix
Author-email: zumix.cpp@gmail.com
License: MIT
Platform: any
Classifier: Development Status :: 5 - Production/Stable
Classifier: Topic :: Utilities
Classifier: License :: OSI Approved :: MIT License
Classifier: Programming Language :: Python
Classifier: Programming Language :: Python :: 3.8
Classifier: Programming Language :: Python :: 3.9
Requires-Python: >3.4
Requires-Dist: pyknp
Requires-Dist: python-Levenshtein
Requires-Dist: pyxDamerauLevenshtein
Requires-Dist: jaconv
Requires-Dist: html2text
Requires-Dist: pyyaml
Provides-Extra: test
Requires-Dist: importlib-metadata (<2,>=0.12) ; extra == 'test'
Requires-Dist: tox ; extra == 'test'
Requires-Dist: tox-pyenv ; extra == 'test'
Requires-Dist: pytest ; extra == 'test'
